cldf_ldd/__init__.py
cldf_ldd/cldf.py
cldf_ldd/components/__init__.py
cldf_ldd/components/columns.json
cldf_ldd/components/constructions/ConstructionTable-metadata.json
cldf_ldd/components/constructions/README.md
cldf_ldd/components/constructions/description.md
cldf_ldd/components/derivationalprocesses/DerivProcTable-metadata.json
cldf_ldd/components/derivationalprocesses/README.md
cldf_ldd/components/derivationalprocesses/description.md
cldf_ldd/components/derivations/DerivationTable-metadata.json
cldf_ldd/components/derivations/README.md
cldf_ldd/components/derivations/description.md
cldf_ldd/components/exampleparts/ExampleParts-metadata.json
cldf_ldd/components/exampleparts/README.md
cldf_ldd/components/exampleparts/description.md
cldf_ldd/components/formparts/FormParts-metadata.json
cldf_ldd/components/formparts/README.md
cldf_ldd/components/formparts/description.md
cldf_ldd/components/formstems/FormStems-metadata.json
cldf_ldd/components/formstems/README.md
cldf_ldd/components/formstems/description.md
cldf_ldd/components/glosses/GlossTable-metadata.json
cldf_ldd/components/glosses/README.md
cldf_ldd/components/glosses/description.md
cldf_ldd/components/inflectionalcategories/InflCatTable-metadata.json
cldf_ldd/components/inflectionalcategories/README.md
cldf_ldd/components/inflectionalcategories/description.md
cldf_ldd/components/inflectionalvalues/InflValTable-metadata.json
cldf_ldd/components/inflectionalvalues/README.md
cldf_ldd/components/inflectionalvalues/description.md
cldf_ldd/components/inflections/InflectionTable-metadata.json
cldf_ldd/components/inflections/README.md
cldf_ldd/components/inflections/description.md
cldf_ldd/components/keys.yaml
cldf_ldd/components/lexemes/LexemeTable-metadata.json
cldf_ldd/components/lexemes/README.md
cldf_ldd/components/lexemes/description.md
cldf_ldd/components/morphemes/MorphemeTable-metadata.json
cldf_ldd/components/morphemes/README.md
cldf_ldd/components/morphemes/description.md
cldf_ldd-0.0.10.dist-info/LICENSE
cldf_ldd-0.0.10.dist-info/METADATA
cldf_ldd-0.0.10.dist-info/WHEEL
cldf_ldd-0.0.10.dist-info/entry_points.txt
cldf_ldd-0.0.10.dist-info/RECORD
